qa_tests
