Metadata-Version: 1.1
Name: qa-tests
Version: 0.3.0
Summary: QA tests tools
Home-page: http://confluence/pages/viewpage.action?pageId=20616082
Author: Mappy QA Team
Author-email: dt.qa@mappy.com
License: UNKNOWN
Platform: UNKNOWN
Classifier: Programming Language :: Python :: 2.7
Classifier: Operating System :: POSIX :: Linux
